brymck/__init__.py
brymck/securities/__init__.py
brymck/securities/v1/__init__.py
brymck/securities/v1/price_pb2.py
brymck/securities/v1/price_pb2_grpc.py
brymck/securities/v1/securities_api_pb2.py
brymck/securities/v1/securities_api_pb2_grpc.py
brymck/securities/v1/security_pb2.py
brymck/securities/v1/security_pb2_grpc.py
brymck_securities-0.0.5.dist-info/METADATA
brymck_securities-0.0.5.dist-info/WHEEL
brymck_securities-0.0.5.dist-info/top_level.txt
brymck_securities-0.0.5.dist-info/RECORD
